sshutil/__init__.py
sshutil/cache.py
sshutil/cmd.py
sshutil/conn.py
sshutil/host.py
sshutil/server.py
sshutil-1.5.0.dist-info/DESCRIPTION.rst
sshutil-1.5.0.dist-info/METADATA
sshutil-1.5.0.dist-info/RECORD
sshutil-1.5.0.dist-info/WHEEL
sshutil-1.5.0.dist-info/metadata.json
sshutil-1.5.0.dist-info/pbr.json
sshutil-1.5.0.dist-info/top_level.txt
