Metadata-Version: 1.0
Name: sshutil
Version: 1.5.0
Summary: Python SSH Utility Library
Home-page: https://github.com/choppsv1/pysshutil/
Author: Christian Hopps
Author-email: chopps@gmail.com
License: Apache-2
Platform: UNKNOWN
